theTrial/__init__.py
theTrial/addition.py
theTrial/cli.py
the_trial-2.0.0.dist-info/LICENSE
the_trial-2.0.0.dist-info/METADATA
the_trial-2.0.0.dist-info/WHEEL
the_trial-2.0.0.dist-info/entry_points.txt
the_trial-2.0.0.dist-info/top_level.txt
the_trial-2.0.0.dist-info/RECORD
