Metadata-Version: 2.1
Name: the-trial
Version: 2.0.0
Summary: A Python microframework for easy communication with Kafka.
Author-email: Michael Loukeris <mloukeris@di.uoa.gr>
Project-URL: Changelog, https://github.com/donMichaelL/theTrial
Project-URL: Homepage, https://github.com/donMichaelL/theTrial
Project-URL: Twitter, https://twitter.com/MichaelLoukeris
Keywords: consumer,kafka,microframework,producer,python
Classifier: Development Status :: 3 - Alpha
Classifier: Environment :: Console
Classifier: Intended Audience :: Developers
Classifier: License :: OSI Approved :: MIT License
Classifier: Natural Language :: English
Classifier: Operating System :: OS Independent
Classifier: Programming Language :: Python :: 3 :: Only
Classifier: Programming Language :: Python :: 3.8
Classifier: Programming Language :: Python :: 3.9
Classifier: Programming Language :: Python :: 3.10
Classifier: Programming Language :: Python :: 3.11
Classifier: Programming Language :: Python :: 3.12
Classifier: Programming Language :: Python :: Implementation :: CPython
Classifier: Topic :: Software Development :: Libraries :: Python Modules
Classifier: Typing :: Typed
Requires-Python: >=3.8
License-File: LICENSE
Requires-Dist: click
Requires-Dist: confluent-kafka
Requires-Dist: environs
